cnvrt/__init__.py
cnvrt/client.py
cnvrt/exceptions.py
cnvrt_sdk-1.0.0.dist-info/licenses/LICENSE
cnvrt_sdk-1.0.0.dist-info/METADATA
cnvrt_sdk-1.0.0.dist-info/WHEEL
cnvrt_sdk-1.0.0.dist-info/top_level.txt
cnvrt_sdk-1.0.0.dist-info/RECORD
