Metadata-Version: 2.4
Name: cnvrt-sdk
Version: 1.0.0
Summary: Official Python SDK for CNVRT media conversion API with x402 payment support
Author-email: CNVRT Team <support@cnvrt.ing>
License: MIT
Project-URL: Homepage, https://docs.cnvrt.ing
Project-URL: Documentation, https://docs.cnvrt.ing
Project-URL: Repository, https://github.com/iclipz/cnvrt
Project-URL: Issues, https://github.com/iclipz/cnvrt/issues
Keywords: cnvrt,media-conversion,transcription,x402,payment-protocol,base,solana,usdc,youtube,video-converter,audio-converter,ai-agents
Classifier: Development Status :: 4 - Beta
Classifier: Intended Audience :: Developers
Classifier: License :: OSI Approved :: MIT License
Classifier: Programming Language :: Python :: 3
Classifier: Programming Language :: Python :: 3.8
Classifier: Programming Language :: Python :: 3.9
Classifier: Programming Language :: Python :: 3.10
Classifier: Programming Language :: Python :: 3.11
Classifier: Programming Language :: Python :: 3.12
Classifier: Topic :: Software Development :: Libraries :: Python Modules
Classifier: Topic :: Multimedia :: Sound/Audio :: Conversion
Classifier: Topic :: Multimedia :: Video :: Conversion
Requires-Python: >=3.8
License-File: LICENSE
Requires-Dist: requests>=2.31.0
Provides-Extra: dev
Requires-Dist: pytest>=7.0.0; extra == "dev"
Requires-Dist: pytest-cov>=4.0.0; extra == "dev"
Requires-Dist: black>=23.0.0; extra == "dev"
Requires-Dist: flake8>=6.0.0; extra == "dev"
Requires-Dist: mypy>=1.0.0; extra == "dev"
Dynamic: license-file
